tail_scratch_nn
