Metadata-Version: 1.0
Name: tail-scratch-nn
Version: 1.2
Summary: Neural Network Implementation from scratch
Home-page: UNKNOWN
Author: Itamar Rocha Filho
Author-email: itamardprf@gmail.com
License: UNKNOWN
Platform: UNKNOWN
